nonebot_plugin_multi_source_daily/__init__.py
nonebot_plugin_multi_source_daily/api/__init__.py
nonebot_plugin_multi_source_daily/api/adapter.py
nonebot_plugin_multi_source_daily/api/handlers.py
nonebot_plugin_multi_source_daily/api/manager.py
nonebot_plugin_multi_source_daily/api/parsers.py
nonebot_plugin_multi_source_daily/api/sources/__init__.py
nonebot_plugin_multi_source_daily/api/sources/base.py
nonebot_plugin_multi_source_daily/api/sources/history.py
nonebot_plugin_multi_source_daily/api/sources/ithome.py
nonebot_plugin_multi_source_daily/api/sources/mixins.py
nonebot_plugin_multi_source_daily/api/sources/moyu.py
nonebot_plugin_multi_source_daily/api/sources/sixty_seconds.py
nonebot_plugin_multi_source_daily/api/sources/weibo.py
nonebot_plugin_multi_source_daily/api/sources/zhihu.py
nonebot_plugin_multi_source_daily/commands/__init__.py
nonebot_plugin_multi_source_daily/commands/api.py
nonebot_plugin_multi_source_daily/commands/base.py
nonebot_plugin_multi_source_daily/commands/cache.py
nonebot_plugin_multi_source_daily/commands/news_detail.py
nonebot_plugin_multi_source_daily/commands/schedule.py
nonebot_plugin_multi_source_daily/config.py
nonebot_plugin_multi_source_daily/exceptions.py
nonebot_plugin_multi_source_daily/models.py
nonebot_plugin_multi_source_daily/templates/custom_markdown.css
nonebot_plugin_multi_source_daily/templates/history.html
nonebot_plugin_multi_source_daily/templates/ithome.html
nonebot_plugin_multi_source_daily/templates/news_template.html
nonebot_plugin_multi_source_daily/templates/sixty_seconds.html
nonebot_plugin_multi_source_daily/templates/weibo_hot.html
nonebot_plugin_multi_source_daily/templates/zhihu.html
nonebot_plugin_multi_source_daily/templates/zhihu_hot.html
nonebot_plugin_multi_source_daily/utils/__init__.py
nonebot_plugin_multi_source_daily/utils/cache.py
nonebot_plugin_multi_source_daily/utils/core.py
nonebot_plugin_multi_source_daily/utils/scheduler.py
nonebot_plugin_multi_source_daily/utils/screenshot.py
nonebot_plugin_multi_source_daily-0.3.0.dist-info/LICENSE
nonebot_plugin_multi_source_daily-0.3.0.dist-info/METADATA
nonebot_plugin_multi_source_daily-0.3.0.dist-info/WHEEL
nonebot_plugin_multi_source_daily-0.3.0.dist-info/RECORD
