Metadata-Version: 2.1
Name: nonebot-plugin-multi-source-daily
Version: 0.3.0
Summary: 一个聚合多种日报源的NoneBot2插件，支持定时发送和多API源
Home-page: https://github.com/webjoin111/nonebot-plugin-multi-source-daily
License: MIT
Keywords: nonebot,nonebot2,daily,news,aggregator
Author: webjoin111
Author-email: 455457521@qq.com
Requires-Python: >=3.8,<4.0
Classifier: License :: OSI Approved :: MIT License
Classifier: Programming Language :: Python :: 3
Classifier: Programming Language :: Python :: 3.8
Classifier: Programming Language :: Python :: 3.9
Classifier: Programming Language :: Python :: 3.10
Classifier: Programming Language :: Python :: 3.11
Classifier: Programming Language :: Python :: 3.12
Classifier: Programming Language :: Python :: 3.13
Provides-Extra: image
Requires-Dist: httpx (>=0.23.0,<1.0.0)
Requires-Dist: nonebot-adapter-onebot (>=2.0.0,<3.0.0)
Requires-Dist: nonebot-plugin-alconna (>=0.30.0)
Requires-Dist: nonebot-plugin-apscheduler (>=0.3.0)
Requires-Dist: nonebot-plugin-htmlrender (>=0.2.0)
Requires-Dist: nonebot-plugin-localstore (>=0.4.0)
Requires-Dist: nonebot2 (>=2.3.0)
Project-URL: Repository, https://github.com/webjoin111/nonebot-plugin-multi-source-daily
